authentication_validation/__init__.py
authentication_validation/cognito_validation.py
authentication_validation/test_cognito_validation.py
sts_validate_authentication_aws_cognito_tj-0.0.8.dist-info/METADATA
sts_validate_authentication_aws_cognito_tj-0.0.8.dist-info/WHEEL
sts_validate_authentication_aws_cognito_tj-0.0.8.dist-info/top_level.txt
sts_validate_authentication_aws_cognito_tj-0.0.8.dist-info/RECORD
