Metadata-Version: 2.1
Name: sts-validate-authentication-aws-cognito-tj
Version: 0.0.8
Summary: authentication validation for sts with aws cognito implementation
Home-page: https://github.com/tbindseil/sts-mono-repo
Author: tj
Author-email: tjbindseil@gmail.com
License: UNKNOWN
Platform: UNKNOWN
Classifier: Programming Language :: Python :: 3
Classifier: License :: OSI Approved :: MIT License
Classifier: Operating System :: OS Independent
Requires-Python: >=3.6
Requires-Dist: python-jose
Requires-Dist: requests
